Metadata-Version: 2.1
Name: xontrib-chatgpt
Version: 0.2.2
Summary: Gives the ability to use ChatGPT directly from the command line
Author-email: Justin Pallansch <pallanschja@gmail.com>
License: MIT License
Project-URL: Homepage, https://github.com/jpal91/xontrib-chatgpt
Project-URL: Documentation, https://github.com/jpal91/xontrib-chatgpt/blob/master/README.md
Project-URL: Code, https://github.com/jpal91/xontrib-chatgpt
Project-URL: Issue tracker, https://github.com/jpal91/xontrib-chatgpt/issues
Platform: any
Classifier: Programming Language :: Python :: 3
Classifier: License :: OSI Approved :: MIT License
Classifier: Operating System :: OS Independent
Classifier: Topic :: System :: Shells
Classifier: Topic :: System :: System Shells
Classifier: Topic :: Terminals
Requires-Python: >=3.9
License-File: LICENSE
Requires-Dist: xonsh >=0.12.5
Requires-Dist: prompt-toolkit >=3.0.36
Requires-Dist: openai <1,>=0.28.0
Requires-Dist: pygments >=2.16.1
Requires-Dist: tiktoken >=0.5.1
Provides-Extra: dev
Requires-Dist: pytest >=7.0 ; extra == 'dev'
Requires-Dist: pyyaml >=0.2.5 ; extra == 'dev'
Provides-Extra: yaml
Requires-Dist: pyyaml >=0.2.5 ; extra == 'yaml'
